pushbullet_tools/__init__.py
pushbullet_tools/push_message.py
pushbullet_tools-0.0.7.dist-info/LICENSE
pushbullet_tools-0.0.7.dist-info/METADATA
pushbullet_tools-0.0.7.dist-info/WHEEL
pushbullet_tools-0.0.7.dist-info/entry_points.txt
pushbullet_tools-0.0.7.dist-info/top_level.txt
pushbullet_tools-0.0.7.dist-info/RECORD
