Metadata-Version: 2.1
Name: pushbullet-tools
Version: 0.0.7
Summary: package for interacting with pushbullet via python
Home-page: https://github.com/nubs01/pushbullet_tools
Author: Roshan Nanu
Author-email: roshan.nanu@gmail.com
License: MIT
Keywords: pushbullet pbmsg push message push_message alert code_alert push_alert notifications push_notification notify python package pushbullet_tools
Platform: UNKNOWN
Classifier: Programming Language :: Python :: 3.6
Classifier: Programming Language :: Python :: 3.7
Classifier: Operating System :: OS Independent
Classifier: License :: OSI Approved :: MIT License
Requires-Python: >=3.6
Requires-Dist: keyring
Requires-Dist: requests
